{
    "title": "Free",
    "description": "",
    "params": {
        "rounded": 0,
		"shadow": 0,
		"gradient": 1,
		"labels_position": "above",
		"labels_invalid_color": "#AA0000",
		"text_color": "",
		"form_font_size": "",
		"form_font_family": "",
		"fields_color": "",
		"fields_border_color": "",
		"fields_text_color": "",
		"fields_active_color": "",
		"fields_active_border_color": "",
		"fields_active_text_color": "",
		"fields_invalid_color": "",
		"fields_invalid_border_color": "#AA0000",
		"fields_invalid_text_color": "#AA0000",
		"buttons_fields_color": "",
		"buttons_text_color": "",
		"bg_color": "",
		"bg_opacity": "",
		"bg_padding_position": "",
		"bg_padding": "",
		"bg_image": "",
		"bg_position": "",
		"bg_repeat": "",
		"bg_size": "",
		"toggler_bg": "",
		"toggler_color": "",
		"toggler_icon": "",
		"toggler_glyphicon": "",
		"toggler_icon_gallery_image": "",
		"toggler_icon_custom_image": "",
		"toggler_font_size": "",
		"toggler_font_family": "",
		"msg_success_color": "",
		"msg_error_color": ""
    }
}